open2listen/__init__.py
open2listen/displaytext.py
open2listen/pdf2text.py
open2listen/texttoaudio.py
open2listen-0.1.0.dist-info/LICENSE
open2listen-0.1.0.dist-info/METADATA
open2listen-0.1.0.dist-info/WHEEL
open2listen-0.1.0.dist-info/top_level.txt
open2listen-0.1.0.dist-info/RECORD
